[
    {
        "key": "dbln",
        "value": "%7B%2261557007724210%22%3A%22iV45V1ND%22%2C%2261556671226989%22%3A%228nh1NxnM%22%2C%2261560789780748%22%3A%22kBbYplZH%22%2C%2261567031395506%22%3A%22ZcWV6DHB%22%2C%2261558085399567%22%3A%22sQNR3SpR%22%2C%22100040751131479%22%3A%22FwPClGkh%22%2C%2261568437890047%22%3A%22thv9rZgV%22%2C%2261564242296665%22%3A%22TQJ1wa2F%22%2C%22100062192141681%22%3A%22UkIh2R2o%22%2C%2261567693260118%22%3A%22Cs5UhtGg%22%2C%2261553473858722%22%3A%22vdnESGBo%22%7D",
        "domain": "facebook.com",
        "path": "/login/device-based/",
        "hostOnly": false,
        "creation": "2024-11-16T11:30:03.727Z",
        "lastAccessed": "2024-11-16T11:30:03.727Z"
    },
    {
        "key": "datr",
        "value": "WJfKZo8jk-Gf0jB-mcBx376l",
        "domain": "facebook.com",
        "path": "/",
        "hostOnly": false,
        "creation": "2024-11-16T11:30:03.727Z",
        "lastAccessed": "2024-11-16T11:30:03.727Z"
    },
    {
        "key": "sb",
        "value": "WJfKZiotpmCJ_5S1PI9t7fET",
        "domain": "facebook.com",
        "path": "/",
        "hostOnly": false,
        "creation": "2024-11-16T11:30:03.727Z",
        "lastAccessed": "2024-11-16T11:30:03.727Z"
    },
    {
        "key": "vpd",
        "value": "v1%3B575x314x3.43505597114563",
        "domain": "facebook.com",
        "path": "/",
        "hostOnly": false,
        "creation": "2024-11-16T11:30:03.727Z",
        "lastAccessed": "2024-11-16T11:30:03.727Z"
    },
    {
        "key": "ps_l",
        "value": "1",
        "domain": "facebook.com",
        "path": "/",
        "hostOnly": false,
        "creation": "2024-11-16T11:30:03.728Z",
        "lastAccessed": "2024-11-16T11:30:03.728Z"
    },
    {
        "key": "ps_n",
        "value": "1",
        "domain": "facebook.com",
        "path": "/",
        "hostOnly": false,
        "creation": "2024-11-16T11:30:03.728Z",
        "lastAccessed": "2024-11-16T11:30:03.728Z"
    },
    {
        "key": "locale",
        "value": "bn_IN",
        "domain": "facebook.com",
        "path": "/",
        "hostOnly": false,
        "creation": "2024-11-16T11:30:03.728Z",
        "lastAccessed": "2024-11-16T11:30:03.728Z"
    },
    {
        "key": "m_pixel_ratio",
        "value": "3.43505597114563",
        "domain": "facebook.com",
        "path": "/",
        "hostOnly": false,
        "creation": "2024-11-16T11:30:03.728Z",
        "lastAccessed": "2024-11-16T11:30:03.728Z"
    },
    {
        "key": "c_user",
        "value": "61553473858722",
        "domain": "facebook.com",
        "path": "/",
        "hostOnly": false,
        "creation": "2024-11-16T11:30:03.728Z",
        "lastAccessed": "2024-11-16T11:30:03.728Z"
    },
    {
        "key": "fr",
        "value": "0t9ipHjYZqRrvVHmF.AWVnoH018L1ocngvSiP9P0pSPLU.BnMgZ-..AAA.0.0.BnOIIz.AWXMN20Zbx8",
        "domain": "facebook.com",
        "path": "/",
        "hostOnly": false,
        "creation": "2024-11-16T11:30:03.728Z",
        "lastAccessed": "2024-11-16T11:30:03.728Z"
    },
    {
        "key": "xs",
        "value": "49%3AZ14WeD36UjCX3g%3A2%3A1731756595%3A-1%3A5173",
        "domain": "facebook.com",
        "path": "/",
        "hostOnly": false,
        "creation": "2024-11-16T11:30:03.728Z",
        "lastAccessed": "2024-11-16T11:30:03.728Z"
    },
    {
        "key": "wd",
        "value": "315x575",
        "domain": "facebook.com",
        "path": "/",
        "hostOnly": false,
        "creation": "2024-11-16T11:30:03.728Z",
        "lastAccessed": "2024-11-16T11:30:03.728Z"
    },
    {
        "key": "wl_cbv",
        "value": "v2%3Bclient_version%3A2675%3Btimestamp%3A1731756600",
        "domain": "facebook.com",
        "path": "/",
        "hostOnly": false,
        "creation": "2024-11-16T11:30:03.728Z",
        "lastAccessed": "2024-11-16T11:30:03.728Z"
    },
    {
        "key": "fbl_st",
        "value": "100631225%3BT%3A28862610",
        "domain": "facebook.com",
        "path": "/",
        "hostOnly": false,
        "creation": "2024-11-16T11:30:03.728Z",
        "lastAccessed": "2024-11-16T11:30:03.728Z"
    }
]
